social_insight_summarizer/__init__.py
social_insight_summarizer/main.py
social_insight_summarizer/prompts.py
social_insight_summarizer-2025.12.21113835.dist-info/METADATA
social_insight_summarizer-2025.12.21113835.dist-info/WHEEL
social_insight_summarizer-2025.12.21113835.dist-info/top_level.txt
social_insight_summarizer-2025.12.21113835.dist-info/RECORD
