Metadata-Version: 2.4
Name: social-insight-summarizer
Version: 2025.12.21113835
Summary: A new package is designed to receive a brief description of social media activity within an organization and analyze it to generate a structured summary highlighting key trends, comparisons, and insig
Author-email: social-insight-summarizer <hi@eugene.plus>
License: MIT
Project-URL: Homepage, https://github.com/chigwell/social-insight-summarizer
Requires-Python: >=3.9
Requires-Dist: langchain-llm7>=0.0.0
Requires-Dist: llmatch-messages>=0.0.0
Requires-Dist: langchain-core>=0.3.0
